{
  "brand": {
    "name": "Dental Woda",
    "shortName": "Woda",
    "logo": {
      "type": "text"
    }
  },
  "theme": {
    "primary": "#073677",
    "accent": "#0588D7",
    "label": "#09357C",
    "bgSoft": "#F9F9FB",
    "footerBg": "#0A1F3D",
    "footerText": "#FFFFFF",
    "text": "#1A1A1A"
  },
  "contact": {
    "whatsapp": {
      "phone": "5491173624454",
      "defaultMessage": "Hola, quiero reservar un turno en Dental Woda."
    },
    "phoneDisplay": "+54 9 11 7362-4454",
    "address": "Marcelo T. de Alvear 2163, Piso 5, Recoleta",
    "hours": "Lun a Vie · 9 a 20hs · Sáb 9 a 15hs",
    "mapQuery": "Marcelo Torcuato de Alvear 2163, C1122 Ciudad Autónoma de Buenos Aires, Argentina"
  },
  "seo": {
    "baseUrl": "https://dental-woda.kingdom-tech.co",
    "title": "Dental Woda — Odontología digital en Recoleta | Scan 3D sin moldes",
    "description": "Clínica odontológica en Recoleta, CABA. Tecnología digital, coronas y carillas sin moldes, blanqueamiento e implantes. 4.9★ con 498 opiniones en Google.",
    "ogTitle": "Dental Woda — Odontología digital en Recoleta",
    "ogDescription": "Clínica odontológica en Recoleta. Scan digital sin moldes, blanqueamiento e implantes. 4.9★ con 498 opiniones.",
    "siteName": "Dental Woda",
    "locale": "es_AR",
    "htmlLang": "es",
    "twitterDescription": "Clínica odontológica en Recoleta. Scan digital, blanqueamiento e implantes. 4.9★ con 498 opiniones.",
    "noindex": true,
    "structuredData": {
      "type": "Dentist",
      "address": {
        "street": "Marcelo T. de Alvear 2163, Piso 5",
        "city": "Ciudad Autónoma de Buenos Aires",
        "region": "CABA",
        "postalCode": "C1122",
        "country": "AR"
      },
      "geo": {
        "lat": -34.5958,
        "lng": -58.3967
      },
      "hours": [
        {
          "days": [
            "Monday",
            "Tuesday",
            "Wednesday",
            "Thursday",
            "Friday"
          ],
          "opens": "09:00",
          "closes": "20:00"
        },
        {
          "days": [
            "Saturday"
          ],
          "opens": "09:00",
          "closes": "15:00"
        }
      ],
      "rating": {
        "value": 4.9,
        "count": 498
      }
    }
  },
  "nav": [
    {
      "label": "Inicio",
      "href": "#inicio"
    },
    {
      "label": "Servicios",
      "href": "#servicios"
    },
    {
      "label": "Metodología",
      "href": "#metodologia"
    },
    {
      "label": "Nosotros",
      "href": "#nosotros"
    },
    {
      "label": "Testimonios",
      "href": "#testimonios"
    },
    {
      "label": "FAQ",
      "href": "#faq"
    },
    {
      "label": "Turnos",
      "href": "#contacto"
    }
  ],
  "cta": {
    "primaryLabel": "Reservá Turno",
    "contactLabel": "Contactanos"
  },
  "sections": {
    "hero": {
      "eyebrow": "M. T. de Alvear 2163 · Recoleta · CABA",
      "headline": [
        {
          "text": "Expertos en\n"
        },
        {
          "text": "Odontologia",
          "accent": true
        }
      ],
      "subheadline": "Tecnología digital y atención cálida\npara cuidar cada detalle de tu sonrisa.",
      "ctaLabel": "Reservá Turno",
      "image": "/img/hero-7.jpg",
      "laurel": {
        "brand": "4.9 ★",
        "label": "498 opiniones en Google"
      },
      "stats": [
        {
          "value": "4.9",
          "label": "★★★★★",
          "labelStyle": "stars"
        },
        {
          "value": "498",
          "label": "Reviews"
        },
        {
          "value": "Scan 3D",
          "label": "Sin moldes"
        }
      ]
    },
    "services": {
      "eyebrow": "Servicios",
      "heading": [
        {
          "text": "Tratamientos dentales\n"
        },
        {
          "text": "Con tecnología digital",
          "accent": true
        }
      ],
      "items": [
        {
          "name": "Estética dental",
          "image": "/img/estetica.jpg"
        },
        {
          "name": "Blanqueamiento",
          "image": "/img/estetica.jpg"
        },
        {
          "name": "Implantes",
          "image": "/img/implantes.jpg"
        },
        {
          "name": "Ortodoncia",
          "image": "/img/brackets.jpg"
        },
        {
          "name": "Cirugía y extracciones",
          "image": "/img/ondodoncia.jpg"
        },
        {
          "name": "Endodoncia",
          "image": "/img/ondodoncia.jpg"
        },
        {
          "name": "Prótesis y coronas",
          "image": "/img/protesis.jpg"
        },
        {
          "name": "Urgencias",
          "image": "/img/emergencia.jpg"
        }
      ]
    },
    "methodology": {
      "eyebrow": "Metodología",
      "paragraph": [
        {
          "text": "Escaneamos tu boca en 3D en lugar de tomar moldes. Coronas y carillas resueltas en pocas visitas, "
        },
        {
          "text": "con un equipo que te explica cada paso.",
          "accent": true
        }
      ],
      "cards": [
        {
          "type": "content",
          "title": "Scan digital\nSin moldes",
          "body": "Usamos escáner intraoral para diseñar coronas, carillas y tratamientos con precisión milimétrica. Menos visitas, cero moldes incómodos, resultados exactos."
        },
        {
          "type": "image",
          "image": "/img/metodology-1.jpg"
        },
        {
          "type": "content",
          "title": "4.9/5 Calificación\nPromedio",
          "body": "498 pacientes nos eligieron y nos calificaron en Google. Turnos rápidos, trato cálido y equipo preparado para que incluso si le tenés miedo al dentista te sientas tranquilo."
        },
        {
          "type": "image",
          "image": "/img/heart.jpg"
        }
      ]
    },
    "team": {
      "eyebrow": "Sobre Nosotros",
      "heading": [
        {
          "text": "Conocé El Equipo\n"
        },
        {
          "text": "Detrás De Tu Sonrisa",
          "accent": true
        }
      ],
      "members": [
        {
          "name": "Dra. Mercedes Brusco",
          "role": "Estética · Blanqueamiento",
          "experience": "AÑOS DE EXP",
          "image": "/img/team-1.jpg"
        },
        {
          "name": "Dr. Juan Genoud",
          "role": "Odontología general",
          "experience": "AÑOS DE EXP",
          "image": "/img/team-2.jpg"
        },
        {
          "name": "Dra. Nicole Brasquet",
          "role": "Implantología · Cirugía",
          "experience": "AÑOS DE EXP",
          "image": "/img/team-3.jpg"
        },
        {
          "name": "Dr. Enrique Portinari",
          "role": "Odontología general",
          "experience": "AÑOS DE EXP",
          "image": "/img/team-4.jpg"
        }
      ]
    },
    "testimonials": {
      "eyebrow": "Testimonios",
      "heading": [
        {
          "text": "Pacientes que\n"
        },
        {
          "text": "Nos recomiendan",
          "accent": true
        }
      ],
      "items": [
        {
          "quote": "Altamente recomendable. Gran profesionalismo de los doctores, y los chicos de recepción son muy amables y empáticos. Excelente atención y el lugar muy limpio. Mi Dra. Camila Fontana es una genia.",
          "name": "Susana Irala",
          "rating": 5,
          "gender": "female"
        },
        {
          "quote": "Muy agradecida con todos, me atendió la Dra. Martina. Nunca me habían dado anestesia tan suavemente, no sentí absolutamente nada. Las chicas de recepción amorosas y el lugar impecable, voy a volver.",
          "name": "Ornella Vizconti",
          "rating": 5,
          "gender": "female"
        },
        {
          "quote": "Como paciente con un miedo importante a los dentistas, me siento en la obligación de recomendar este lugar. Excelentes profesionales desde la recepción hasta la doctora Mercedes Brusco, una genia con su técnica.",
          "name": "Rosario Cardozo",
          "rating": 5,
          "gender": "female"
        },
        {
          "quote": "Felicito a Dental Woda y sus profesionales por el trabajo hiper profesional que hacen, con última tecnología, y dando soluciones verdaderas a las necesidades del paciente. Totalmente satisfecho.",
          "name": "Javier Martínez",
          "rating": 5,
          "gender": "male"
        },
        {
          "quote": "Excelente todo: es fácil y rápido sacar un turno, los recepcionistas son amabilísimos y la atención profesional es impecable. Los precios están en relación con el servicio. Te explican todo en detalle.",
          "name": "S. V.",
          "rating": 5,
          "gender": "female"
        },
        {
          "quote": "Me realicé una extracción de muela de juicio con la doctora Nicole, una genia. Súper cálida y buena onda. Fueron dos segundos y ya estaba listo, un trabajo espectacular. Muy buen ambiente.",
          "name": "Nicolás Gago",
          "rating": 5,
          "gender": "male"
        },
        {
          "quote": "Excelente trato, muy buenos especialistas. La Dra. Sánchez Fiamma una genia total, me explicó y disipó todas mis dudas. 100% recomendable.",
          "name": "Sebastián Zamudio",
          "rating": 5,
          "gender": "male"
        },
        {
          "quote": "Me atendí hoy, de 10 la verdad, muy rápido. No me atendían en ningún lugar y acá a pesar de estar por cerrar me atendieron con mucha amabilidad y me sacaron el dolor. Re linda la gente y el consultorio.",
          "name": "Maca Diaz",
          "rating": 5,
          "gender": "female"
        },
        {
          "quote": "Estoy muy feliz con la atención recibida en Dental Woda. Me realicé un implante y un tratamiento de ortodoncia, y en todo momento me sentí acompañada, bien informada y en manos de profesionales capacitados.",
          "name": "Noelia Natalino",
          "rating": 5,
          "gender": "female"
        },
        {
          "quote": "Me atiendo en Dental Woda con la Dra. Mercedes, una excelente profesional, atenta y comprometida. Quiero destacar el gran trabajo en equipo y la buena energía. Turnos rápidos y organización impecable.",
          "name": "Anush Ansourian",
          "rating": 5,
          "gender": "female"
        }
      ]
    },
    "faq": {
      "eyebrow": "Preguntas frecuentes",
      "heading": [
        { "text": "Visitanos tranquilo\n" },
        { "text": "Con todo en claro", "accent": true }
      ],
      "items": [
        {
          "question": "¿Atienden obras sociales y prepagas?",
          "answer": "Trabajamos con las principales prepagas y obras sociales. Antes de tu primera consulta escribinos por WhatsApp y confirmamos la cobertura puntual de la tuya."
        },
        {
          "question": "¿Cómo es la primera consulta?",
          "answer": "En la primera visita hacemos un diagnóstico completo, revisamos tu historia clínica y te explicamos las opciones de tratamiento sin compromiso. Recibís toda la información antes de avanzar con cualquier procedimiento."
        },
        {
          "question": "¿Ofrecen financiación o cuotas?",
          "answer": "Sí. Aceptamos todas las tarjetas y, según el tratamiento, ofrecemos planes en cuotas. Coordinamos un esquema de pago a tu medida en la consulta."
        },
        {
          "question": "¿Atienden urgencias?",
          "answer": "Sí, reservamos turnos para urgencias en el mismo día. Escribinos por WhatsApp y coordinamos la atención lo antes posible."
        },
        {
          "question": "¿Atienden a niños?",
          "answer": "Si necesitás atención odontopediátrica escribinos por WhatsApp y te orientamos."
        },
        {
          "question": "¿Dónde están y cuáles son los horarios?",
          "answer": "Estamos en Marcelo T. de Alvear 2163, Piso 5, Recoleta. Atendemos de lunes a viernes de 9 a 20hs y los sábados de 9 a 15hs. Podés ver la ubicación exacta en el mapa al final de la página."
        }
      ]
    },
    "contactCta": {
      "eyebrow": "Reservá turno",
      "heading": [
        {
          "text": "Tu mejor sonrisa\n"
        },
        {
          "text": "Te está esperando",
          "accent": true
        }
      ],
      "description": "Te respondemos por WhatsApp en minutos\ny coordinamos tu primera consulta.",
      "ctaLabel": "Reservar por WhatsApp",
      "addressLine": "M. T. de Alvear 2163, Piso 5 · Recoleta",
      "hoursLine": "Lun a Vie 9-20hs · Sáb 9-15hs",
      "mapTitle": "Ubicación de la clínica"
    },
    "footer": {
      "about": "Clínica odontológica en Recoleta, CABA.\nTecnología digital, blanqueamiento\ne implantes con atención cálida.",
      "socials": [
        {
          "label": "WhatsApp",
          "whatsapp": true,
          "external": true
        }
      ],
      "columns": [
        {
          "heading": "Navegar",
          "items": [
            {
              "label": "Servicios",
              "href": "#servicios"
            },
            {
              "label": "Metodología",
              "href": "#metodologia"
            },
            {
              "label": "Nosotros",
              "href": "#nosotros"
            },
            {
              "label": "Testimonios",
              "href": "#testimonios"
            }
          ]
        },
        {
          "heading": "Servicios",
          "items": [
            {
              "label": "Estética dental",
              "href": "#servicios"
            },
            {
              "label": "Implantes",
              "href": "#servicios"
            },
            {
              "label": "Ortodoncia",
              "href": "#servicios"
            },
            {
              "label": "Blanqueamiento",
              "href": "#servicios"
            }
          ]
        },
        {
          "heading": "Contacto",
          "items": [
            {
              "label": "M. T. de Alvear 2163, Piso 5"
            },
            {
              "label": "+54 9 11 7362-4454",
              "whatsapp": true,
              "external": true
            },
            {
              "label": "Lun a Vie 9-20hs · Sáb 9-15hs",
              "muted": true
            }
          ]
        }
      ],
      "copyrightName": "Dental Woda"
    }
  }
}
